pyqt_liquidglass/__init__.py
pyqt_liquidglass/_bridge.py
pyqt_liquidglass/_compat.py
pyqt_liquidglass/_platform.py
pyqt_liquidglass/_types.py
pyqt_liquidglass/glass.py
pyqt_liquidglass/helpers.py
pyqt_liquidglass/py.typed
pyqt_liquidglass/traffic_lights.py
pyqt_liquidglass-0.1.0.dist-info/WHEEL
pyqt_liquidglass-0.1.0.dist-info/METADATA
pyqt_liquidglass-0.1.0.dist-info/RECORD
