Metadata-Version: 2.3
Name: pyqt-liquidglass
Version: 0.1.0
Summary: macOS Liquid Glass effects for PySide6 and PyQt6
Keywords: pyqt,pyside,qt,macos,liquid glass,blur,vibrancy,nsvisualeffectview
Author: h
Author-email: h <h@kotikot.com>
License: Copyright (c) 2026 h
Classifier: Intended Audience :: Developers
Classifier: Topic :: Desktop Environment
Classifier: Topic :: Software Development :: Libraries :: Python Modules
Classifier: Topic :: Software Development :: User Interfaces
Classifier: License :: OSI Approved :: MIT License
Classifier: Programming Language :: Python :: 3
Classifier: Programming Language :: Python :: 3.12
Classifier: Programming Language :: Python :: 3.13
Classifier: Operating System :: MacOS
Classifier: Typing :: Typed
Requires-Dist: pyobjc-framework-cocoa>=12.1
Requires-Dist: pyobjc-framework-quartz>=12.1
Requires-Python: >=3.12
Project-URL: Homepage, https://git.kotikot.com/lib/pyqt-liquidglass
Project-URL: Documentation, https://pyqt-liquidglass.readthedocs.io
Project-URL: Repository, https://github.com/kotikotprojects/pyqt-liquidglass
